HDDFeatures/__init__.py
HDDFeatures/discernibleScore.py
HDDFeatures/fastFeatureSelectionDS.py
HDDFeatures/increDiscernibleScore.py
HDDFeatures/increFeaSltDSFilterSam.py
HDDFeatures/increFeatureSelectionDS.py
HDDFeatures/partition_fold.py
HDDFeatures-0.1.1.dist-info/METADATA
HDDFeatures-0.1.1.dist-info/WHEEL
HDDFeatures-0.1.1.dist-info/top_level.txt
HDDFeatures-0.1.1.dist-info/RECORD
